strangeloop/__init__.py
strangeloop/cli.py
strangeloop/config.py
strangeloop/llm.py
strangeloop-0.1.0.dist-info/METADATA
strangeloop-0.1.0.dist-info/WHEEL
strangeloop-0.1.0.dist-info/entry_points.txt
strangeloop-0.1.0.dist-info/top_level.txt
strangeloop-0.1.0.dist-info/RECORD
