Metadata-Version: 2.2
Name: strangeloop
Version: 0.1.0
Summary: A recursive and self-referential AI agent framework
Requires-Python: >=3.13
Requires-Dist: click>=8.1.8
Requires-Dist: requests>=2.32.3
